{"annotatable":{"parts":["s1v1"]},"anncomplete":false,"sources":[],"metas":{},"entities":[{"classId":"e_45","part":"s1v1","offsets":[{"start":0,"text":"이라크 전쟁"}],"coordinates":[],"confidence":{"state":"pre-added","who":["user:Nonegom"],"prob":1},"fields":{},"normalizations":{}},{"classId":"e_50","part":"s1v1","offsets":[{"start":12,"text":"2003년"}],"coordinates":[],"confidence":{"state":"pre-added","who":["user:Nonegom"],"prob":1},"fields":{},"normalizations":{}}],"relations":[{"classId":"r_72","type":"linked","directed":false,"entities":["s1v1|e_50|12,16","s1v1|e_45|0,5"],"confidence":{"state":"pre-added","who":["user:Nonegom"],"prob":1}}]}